[{"pos": "epubcfi(/18/2/4/702/1:0)", "pos_type": "epubcfi", "timestamp": "2024-01-19T20:49:08.652084+00:00", "type": "last-read"}, {"end_cfi": "/2/4/644/1:223", "highlighted_text": "“closer and closer”", "spine_index": 8, "spine_name": "OEBPS/html/0486660974_08_chapter02.html", "start_cfi": "/2/4/644/1:204", "style": {"dark": "#cccc00", "friendly_name": "neon_green", "kind": "color", "light": "#00ffaa", "type": "custom"}, "timestamp": "2024-01-19T20:40:41.710Z", "toc_family_titles": ["Chapter 2 Differential Calculus", "2.4. Derivatives and Limits"], "type": "highlight", "uuid": "w2If1aE_n6kgOtQbVBOiyg"}, {"end_cfi": "/2/4/664/12/1:5", "highlighted_text": "limit", "spine_index": 8, "spine_name": "OEBPS/html/0486660974_08_chapter02.html", "start_cfi": "/2/4/664/12/1:0", "style": {"dark": "#cccc00", "friendly_name": "cyan", "kind": "color", "light": "#00ffff", "type": "custom"}, "timestamp": "2024-01-19T20:42:01.142Z", "toc_family_titles": ["Chapter 2 Differential Calculus", "2.4. Derivatives and Limits"], "type": "highlight", "uuid": "nowUchaAdwWLZl58NmWEUA"}]